README.md
setup.py
osrm_plus/__init__.py
osrm_plus.egg-info/PKG-INFO
osrm_plus.egg-info/SOURCES.txt
osrm_plus.egg-info/dependency_links.txt
osrm_plus.egg-info/not-zip-safe
osrm_plus.egg-info/requires.txt
osrm_plus.egg-info/top_level.txt