Metadata-Version: 1.0
Name: osrm-plus
Version: 0.2.1
Summary: Allow to retrieve both distance and duration matrix for an input list of OSRM coordinates.
Home-page: https://github.com/cglacet/osrm_plus
Author: Christian Glacet
Author-email: christian.glacet@gmail.com
License: MIT
Platform: UNKNOWN
